{"code":200,"total":2,"pageSize":10,"pageCount":1,"data":[{"title":"uniapp(微信小程序) markdown最佳渲染方案","slug":"resource-desk-vue-uniapp-微信小程序-markdown最佳渲染方案","date":"2021-09-17T16:00:00.000Z","img":"/img/header_img/desk/uniapp.png","_id":"clhrbp2d5006ao5lg9ga97g4j","image":"/img/header_img/desk/uniapp.png","project":"desk","subtitle":"markdown最佳渲染方案","updated":"2022-09-20T01:39:11.750Z","num_read":940,"num_like":979,"num_collection":131,"num_comments":216,"author":"Sunfy","comments":true,"path":"api/articles/resource-desk-vue-uniapp-微信小程序-markdown最佳渲染方案.json","excerpt":null,"keywords":null,"cover":null,"covers":["../../../../img/uniapp(微信小程序","../../../../img/uniapp(微信小程序","../../../../img/uniapp(微信小程序","../../../../img/uniapp(微信小程序"],"content":null,"raw":null,"categories":[{"name":"前端","path":"api/categories/前端.json","pathContent":"api/categories/前端"}],"tags":[{"name":"vue","path":"api/tags/vue.json","pathContent":"api/tags/vue"},{"name":"uniapp","path":"api/tags/uniapp.json","pathContent":"api/tags/uniapp"}]},{"title":"uni-app编译到微信报错forceUpdate","slug":"resource-desk-vue-uni-app编译到微信报错forceUpdate","date":"2020-08-17T16:00:00.000Z","img":"/img/header_img/desk/uniapp.png","_id":"clhrbp2d8006go5lggos2bm2m","image":"/img/header_img/desk/uniapp.png","project":"desk","subtitle":"Cannot read property 'forceUpdate' of undefined解决方法","updated":"2022-09-20T01:38:49.763Z","num_read":915,"num_like":835,"num_collection":528,"num_comments":152,"author":"Sunfy","comments":true,"path":"api/articles/resource-desk-vue-uni-app编译到微信报错forceUpdate.json","excerpt":null,"keywords":null,"cover":null,"covers":["../../../../img/uni-app编译到微信报错forceUpdate/webp.webp","../../../../img/uni-app编译到微信报错forceUpdate/image-20211021100814050.png"],"content":null,"raw":null,"categories":[{"name":"前端","path":"api/categories/前端.json","pathContent":"api/categories/前端"}],"tags":[{"name":"vue","path":"api/tags/vue.json","pathContent":"api/tags/vue"},{"name":"uniapp","path":"api/tags/uniapp.json","pathContent":"api/tags/uniapp"}]}],"description":"[uniapp]暂未设置说明","cover":"https://sunfy9.gitee.io/img/header_img/sunfy-default.png"}