{"code":200,"total":34,"pageSize":10,"pageCount":4,"data":[{"title":"Java设计模式之模板模式","slug":"resource-designpattern-behavior-Template","date":"2019-07-05T16:00:00.000Z","img":"/img/header_img/Design/Template.PNG","_id":"clhrbp2az002to5lg2pnmctfn","image":"/img/header_img/Design/Template.PNG","project":"designPattern","updated":"2022-09-20T01:33:05.569Z","num_read":169,"num_like":294,"num_collection":582,"num_comments":278,"comments":true,"hot":"comments","path":"api/articles/resource-designpattern-behavior-Template.json","excerpt":null,"keywords":null,"cover":null,"covers":["../../../../img/Template/template_pattern_uml_diagram.jpg"],"content":null,"raw":null,"categories":[{"name":"设计模式","path":"api/categories/设计模式.json","pathContent":"api/categories/设计模式"}],"tags":[]},{"title":"Java设计模式之策略模式","slug":"resource-designpattern-behavior-Strategy","date":"2019-07-05T16:00:00.000Z","img":"/img/header_img/Design/Strategy.PNG","_id":"clhrbp2b2003ko5lgedi3dsve","image":"/img/header_img/Design/Strategy.PNG","project":"designPattern","updated":"2022-09-20T01:32:54.165Z","num_read":335,"num_like":655,"num_collection":397,"num_comments":177,"comments":true,"hot":"comments","path":"api/articles/resource-designpattern-behavior-Strategy.json","excerpt":null,"keywords":null,"cover":null,"covers":["../../../../img/Strategy/strategy_pattern_uml_diagram.jpg"],"content":null,"raw":null,"categories":[{"name":"设计模式","path":"api/categories/设计模式.json","pathContent":"api/categories/设计模式"}],"tags":[]},{"title":"Java设计模式之建造者模式","slug":"resource-designpattern-build-builder","date":"2019-07-05T16:00:00.000Z","img":"/img/header_img/Design/Builder.PNG","_id":"clhrbp2b7004to5lg34jrcmmt","image":"/img/header_img/Design/Builder.PNG","project":"designPattern","updated":"2022-09-20T01:33:44.974Z","num_read":97,"num_like":670,"num_collection":718,"num_comments":49,"comments":true,"path":"api/articles/resource-designpattern-build-builder.json","excerpt":null,"keywords":null,"cover":null,"covers":["../../../../img/builder/20201015-builder-pattern.svg"],"content":null,"raw":null,"categories":[{"name":"设计模式","path":"api/categories/设计模式.json","pathContent":"api/categories/设计模式"}],"tags":[]},{"title":"Java设计模式之单例模式","slug":"resource-designpattern-build-singleton","date":"2019-07-02T16:00:00.000Z","img":"/img/header_img/Design/Singleton.PNG","_id":"clhrbp2b6004no5lg9sdedbc5","image":"/img/header_img/Design/Singleton.PNG","project":"designPattern","updated":"2022-01-15T04:19:28.000Z","num_read":1173,"num_like":306,"num_collection":689,"num_comments":258,"comments":true,"path":"api/articles/resource-designpattern-build-singleton.json","excerpt":null,"keywords":null,"cover":null,"covers":null,"content":null,"raw":null,"categories":[{"name":"设计模式","path":"api/categories/设计模式.json","pathContent":"api/categories/设计模式"}],"tags":[]}],"description":"简单快捷、解决方案","cover":"https://sunfy9.gitee.io/project/photo/project/design.jpg"}